setup.py
overpunch/__init__.py
overpunch.egg-info/PKG-INFO
overpunch.egg-info/SOURCES.txt
overpunch.egg-info/dependency_links.txt
overpunch.egg-info/top_level.txt
overpunch/tests/__init__.py
overpunch/tests/test_overpunch.py