Metadata-Version: 1.1
Name: overpunch
Version: 1.0
Summary: Overpunch Parser/Formatter
Home-page: http://github.com/truveris/overpunch
Author: Truveris Inc.
Author-email: dev@truveris.com
License: UNKNOWN
Platform: UNKNOWN
Classifier: Intended Audience :: Healthcare Industry
Classifier: Development Status :: 5 - Production/Stable
Classifier: License :: OSI Approved :: MIT License
Classifier: Programming Language :: Python :: 2.7
Classifier: Topic :: Text Processing
